personal_assistant/__init__.py
personal_assistant/addressbook.py
personal_assistant/colorize.py
personal_assistant/command_use.py
personal_assistant/commands.py
personal_assistant/errors.py
personal_assistant/fields.py
personal_assistant/input_parser.py
personal_assistant/main.py
personal_assistant/notes.py
personal_assistant/pickle_data.py
personal_assistant/record.py
personal_assistant/utils.py
pn_assistant-1.0.0.dist-info/licenses/LICENSE
pn_assistant-1.0.0.dist-info/METADATA
pn_assistant-1.0.0.dist-info/WHEEL
pn_assistant-1.0.0.dist-info/entry_points.txt
pn_assistant-1.0.0.dist-info/top_level.txt
pn_assistant-1.0.0.dist-info/RECORD
