Metadata-Version: 2.4
Name: pn-assistant
Version: 1.0.0
Summary: A command-line personal assistant with address book and notes
Home-page: https://github.com/yulikafsd/personal_assistant
Author: PythoNauts
License: MIT
Classifier: Programming Language :: Python :: 3
Classifier: License :: OSI Approved :: MIT License
Classifier: Operating System :: OS Independent
Requires-Python: >=3.9
License-File: LICENSE
Requires-Dist: prettytable>=3.9
Requires-Dist: prompt_toolkit>=3.0
Requires-Dist: colorama>=0.4
Dynamic: license-file
